dolphin/__init__.py
dolphin/version.py
dolphin/TrtWrapper/Engine.py
dolphin/TrtWrapper/__init__.py
dolphin/TrtWrapper/utils/__init__.py
dolphin/TrtWrapper/utils/calibrator.py
dolphin/TrtWrapper/utils/eengine.py
dolphin/TrtWrapper/utils/iengine.py
dolphin/TrtWrapper/utils/image_batcher.py
dolphin/TrtWrapper/utils/logger.py
dolphin/core/__init__.py
dolphin/core/bufferizer.py
dolphin/core/darray.py
dolphin/core/dimage.py
dolphin/core/dtype.py
dolphin/core/trtbuffer.py
dolphin/cutils/__init__.py
dolphin/cutils/bindings.py
dolphin/cutils/compiler_base.py
dolphin/cutils/cuda_base.py
dolphin/cutils/cudarray.py
dolphin/cutils/cudimage.py
dolphin/cutils/cuda/axpbyz.cu
dolphin/cutils/cuda/axpbz.cu
dolphin/cutils/cuda/crop_and_resize.cu
dolphin/cutils/cuda/cvt_color.cu
dolphin/cutils/cuda/discontiguous_copy.cu
dolphin/cutils/cuda/elt_wise_abs.cu
dolphin/cutils/cuda/elt_wise_cast.cu
dolphin/cutils/cuda/elt_wise_div.cu
dolphin/cutils/cuda/elt_wise_mul.cu
dolphin/cutils/cuda/fill.cu
dolphin/cutils/cuda/index_transform.cu
dolphin/cutils/cuda/invscal_div.cu
dolphin/cutils/cuda/normalize.cu
dolphin/cutils/cuda/resize.cu
dolphin/cutils/cuda/scal_div.cu
dolphin/cutils/cuda/transpose.cu
dolphin_python-0.0.10.data/data/dolphin/axpbyz.cu
dolphin_python-0.0.10.data/data/dolphin/axpbz.cu
dolphin_python-0.0.10.data/data/dolphin/crop_and_resize.cu
dolphin_python-0.0.10.data/data/dolphin/cvt_color.cu
dolphin_python-0.0.10.data/data/dolphin/discontiguous_copy.cu
dolphin_python-0.0.10.data/data/dolphin/elt_wise_abs.cu
dolphin_python-0.0.10.data/data/dolphin/elt_wise_cast.cu
dolphin_python-0.0.10.data/data/dolphin/elt_wise_div.cu
dolphin_python-0.0.10.data/data/dolphin/elt_wise_mul.cu
dolphin_python-0.0.10.data/data/dolphin/fill.cu
dolphin_python-0.0.10.data/data/dolphin/index_transform.cu
dolphin_python-0.0.10.data/data/dolphin/invscal_div.cu
dolphin_python-0.0.10.data/data/dolphin/normalize.cu
dolphin_python-0.0.10.data/data/dolphin/resize.cu
dolphin_python-0.0.10.dist-info/LICENSE
dolphin_python-0.0.10.dist-info/METADATA
dolphin_python-0.0.10.dist-info/WHEEL
dolphin_python-0.0.10.dist-info/top_level.txt
dolphin_python-0.0.10.dist-info/RECORD
