Metadata-Version: 2.1
Name: dolphin-python
Version: 0.0.10
Summary: Cuda based library for fast and seamless deep learning inference.
Home-page: https://github.com/MaximeDebarbat/Dolphin
Author: Maxime
Author-email: debarbat.maxime@gmail.com
License: Apache
Platform: UNKNOWN
Classifier: License :: OSI Approved :: Apache Software License
Classifier: Programming Language :: Python
Classifier: Programming Language :: Python :: 3
Classifier: Programming Language :: Python :: 3.6
Requires-Python: >=3.5.0
License-File: LICENSE
Requires-Dist: Jinja2 (==3.1.2)
Requires-Dist: Pillow (==9.4.0)
Requires-Dist: numpy (==1.23.5)
Requires-Dist: onnx
Requires-Dist: opencv-python (==4.5.5.64)
Requires-Dist: pycuda (==2022.2.2)
Requires-Dist: tqdm (==4.65.0)
